[
  {
    "id": 336,
    "callForServiceId": 1001,
    "personId": "88d7bee9-1dec-412e-bf77-b7711ca90268",
    "involvedPerson": {
      "id": "88d7bee9-1dec-412e-bf77-b7711ca90268",
      "namePrefixCodeId": 9,
      "firstName": "Cris",
      "middleName": "Alina",
      "lastName": "MacQuarrie",
      "lastNameSuffixCodeId": null,
      "sortName": "MacQuarrie Cris Alina ",
      "fullName": "Cris Alina MacQuarrie ",
      "streetNumber": null,
      "streetNumberSuffix": null,
      "streetNamePreDirection": null,
      "streetName": null,
      "streetNameSuffix": null,
      "cityName": null,
      "stateName": null,
      "zipCode": null,
      "socialSecurityNumber": null,
      "driversLicenseNumber": null,
      "driversLicenseState": null,
      "driversLicenseClass": null,
      "driversLicenseExpirationDate": null,
      "driversLicenseIssueDate": null,
      "homePhoneNumber": null,
      "workPhoneNumber": null,
      "mobilePhoneNumber": null,
      "dateOfBirth": "1946-01-06T00:00:00",
      "isDeceased": false,
      "dateOfDeath": null,
      "age": 0,
      "ageEnd": 0,
      "genderId": 7,
      "raceId": 4,
      "ethnicityId": null,
      "height": "2'9\"",
      "weight": "105",
      "hairColorId": 16,
      "hairTypeId": 7,
      "eyeColorId": 10,
      "eyewearId": 5,
      "facialHairId": 8,
      "effectiveDateTime": "2018-11-01T20:03:39.0284086",
      "createdUserId": "4ec093f9-9d54-4f84-a8e0-a8124151c9e4",
      "Errors": []
    },
    "contactTypeId": 3,
    "personAddress": null,
    "remarks": null,
    "isAmbulanceRequired": false,
    "callForServiceHospitalId": null,
    "ambulanceRemarks": null,
    "effectiveDateTime": "2019-02-08T20:03:24.840814",
    "createdUserId": "b5b2ec47-615a-40b8-91f6-8a1ba844c0fd",
    "Errors": []
  },
  {
    "id": 2008,
    "callForServiceId": 1001,
    "personId": "07ad3751-c6a9-421d-804e-5d94db6dbc0e",
    "involvedPerson": {
      "id": "07ad3751-c6a9-421d-804e-5d94db6dbc0e",
      "namePrefixCodeId": null,
      "firstName": "Shane",
      "middleName": null,
      "lastName": "Freed",
      "lastNameSuffixCodeId": null,
      "sortName": "Freed Shane ",
      "fullName": "Shane Freed ",
      "streetNumber": null,
      "streetNumberSuffix": null,
      "streetNamePreDirection": null,
      "streetName": null,
      "streetNameSuffix": null,
      "cityName": null,
      "stateName": null,
      "zipCode": null,
      "socialSecurityNumber": null,
      "driversLicenseNumber": null,
      "driversLicenseState": null,
      "driversLicenseClass": null,
      "driversLicenseExpirationDate": null,
      "driversLicenseIssueDate": null,
      "homePhoneNumber": null,
      "workPhoneNumber": null,
      "mobilePhoneNumber": null,
      "dateOfBirth": null,
      "isDeceased": null,
      "dateOfDeath": null,
      "age": null,
      "ageEnd": null,
      "genderId": null,
      "raceId": null,
      "ethnicityId": null,
      "height": null,
      "weight": null,
      "hairColorId": null,
      "hairTypeId": null,
      "eyeColorId": null,
      "eyewearId": null,
      "facialHairId": null,
      "effectiveDateTime": "2019-05-11T04:30:13.9163611",
      "createdUserId": "e513c17a-9150-4bab-944b-6322bb51158f",
      "Errors": []
    },
    "contactTypeId": 1,
    "personAddress": null,
    "remarks": null,
    "isAmbulanceRequired": null,
    "callForServiceHospitalId": null,
    "ambulanceRemarks": null,
    "effectiveDateTime": "2019-05-11T04:30:13.385",
    "createdUserId": "e513c17a-9150-4bab-944b-6322bb51158f",
    "Errors": []
  },
  {
    "id": 2009,
    "callForServiceId": 1001,
    "personId": "a6c6073f-71d0-4589-a242-cc8351affb58",
    "involvedPerson": {
      "id": "a6c6073f-71d0-4589-a242-cc8351affb58",
      "namePrefixCodeId": null,
      "firstName": "Shane",
      "middleName": null,
      "lastName": "Freed",
      "lastNameSuffixCodeId": null,
      "sortName": "Freed Shane ",
      "fullName": "Shane Freed ",
      "streetNumber": null,
      "streetNumberSuffix": null,
      "streetNamePreDirection": null,
      "streetName": null,
      "streetNameSuffix": null,
      "cityName": null,
      "stateName": null,
      "zipCode": null,
      "socialSecurityNumber": null,
      "driversLicenseNumber": null,
      "driversLicenseState": null,
      "driversLicenseClass": null,
      "driversLicenseExpirationDate": null,
      "driversLicenseIssueDate": null,
      "homePhoneNumber": null,
      "workPhoneNumber": null,
      "mobilePhoneNumber": null,
      "dateOfBirth": null,
      "isDeceased": null,
      "dateOfDeath": null,
      "age": null,
      "ageEnd": null,
      "genderId": null,
      "raceId": null,
      "ethnicityId": null,
      "height": null,
      "weight": null,
      "hairColorId": null,
      "hairTypeId": null,
      "eyeColorId": null,
      "eyewearId": null,
      "facialHairId": null,
      "effectiveDateTime": "2019-05-11T04:32:01.6726403",
      "createdUserId": "e513c17a-9150-4bab-944b-6322bb51158f",
      "Errors": []
    },
    "contactTypeId": 1,
    "personAddress": null,
    "remarks": null,
    "isAmbulanceRequired": null,
    "callForServiceHospitalId": null,
    "ambulanceRemarks": null,
    "effectiveDateTime": "2019-05-11T04:30:13.385",
    "createdUserId": "e513c17a-9150-4bab-944b-6322bb51158f",
    "Errors": []
  }
]
